MANIFEST.in
README.rst
setup.py
sixfoh/__init__.py
sixfoh/cli.py
sixfoh.egg-info/PKG-INFO
sixfoh.egg-info/SOURCES.txt
sixfoh.egg-info/dependency_links.txt
sixfoh.egg-info/entry_points.txt
sixfoh.egg-info/top_level.txt