Metadata-Version: 1.0
Name: sixfoh
Version: 0.1.2.3
Summary: Generates base sixfoh-encoded images for yer websites.
Home-page: https://github.com/tylerball/sixfoh
Author: Tyler Ball
Author-email: tyler@tylerball.net
License: BSD
Keywords: base64 encoding images css less
Platform: UNKNOWN
Classifier: Development Status :: 3 - Alpha
Classifier: Environment :: Console
Classifier: License :: OSI Approved :: BSD License
Classifier: Operating System :: OS Independent
Classifier: Topic :: Multimedia :: Graphics :: Graphics Conversion
